ropt_pymoo/__init__.py
ropt_pymoo/config.py
ropt_pymoo/py.typed
ropt_pymoo/pymoo.py
ropt_pymoo/version.py
ropt_pymoo-0.24.1.dist-info/licenses/LICENSE
ropt_pymoo-0.24.1.dist-info/METADATA
ropt_pymoo-0.24.1.dist-info/WHEEL
ropt_pymoo-0.24.1.dist-info/entry_points.txt
ropt_pymoo-0.24.1.dist-info/top_level.txt
ropt_pymoo-0.24.1.dist-info/RECORD
